{
    "core_dimensions": {
        "segmentation_angle": 10, 
        "supplier": "Phillips", 
        "core_type": "EQ", 
        "core_model": "EQ30", 
        "D_1": "30.0", 
        "D_2": "26.0", 
        "D_3": "11.0", 
        "D_4": "20.0", 
        "D_5": "15.0", 
        "D_6": "20.0", 
        "D_7": 0, 
        "D_8": 0, 
        "airgap": {
            "define_airgap": false
        }
    }, 
    "winding_definition": {
        "layer_type": "Wound", 
        "number_of_layers": "10", 
        "layer_spacing": "0.1", 
        "bobbin_board_thickness": "0.1", 
        "top_margin": "0.0", 
        "side_margin": "0.0", 
        "conductor_type": "Rectangular", 
        "include_bobbin": true, 
        "layers_definition": {
            "layer_1": {
                "conductor_width": 0.40000000000000002, 
                "conductor_height": 2.0, 
                "insulation_thickness": 0.050000000000000003, 
                "turns_number": 13
            }, 
            "layer_2": {
                "conductor_width": 0.40000000000000002, 
                "conductor_height": 2.0, 
                "insulation_thickness": 0.050000000000000003, 
                "turns_number": 13
            }, 
            "layer_3": {
                "conductor_width": 0.40000000000000002, 
                "conductor_height": 2.0, 
                "insulation_thickness": 0.050000000000000003, 
                "turns_number": 13
            }, 
            "layer_4": {
                "conductor_width": 0.40000000000000002, 
                "conductor_height": 2.0, 
                "insulation_thickness": 0.050000000000000003, 
                "turns_number": 13
            }, 
            "layer_5": {
                "conductor_width": 0.40000000000000002, 
                "conductor_height": 2.0, 
                "insulation_thickness": 0.050000000000000003, 
                "turns_number": 13
            }, 
            "layer_6": {
                "conductor_width": 0.40000000000000002, 
                "conductor_height": 2.0, 
                "insulation_thickness": 0.050000000000000003, 
                "turns_number": 13
            }, 
            "layer_7": {
                "conductor_width": 0.40000000000000002, 
                "conductor_height": 2.0, 
                "insulation_thickness": 0.050000000000000003, 
                "turns_number": 13
            }, 
            "layer_8": {
                "conductor_width": 0.40000000000000002, 
                "conductor_height": 2.0, 
                "insulation_thickness": 0.050000000000000003, 
                "turns_number": 13
            }, 
            "layer_9": {
                "conductor_width": 0.40000000000000002, 
                "conductor_height": 2.0, 
                "insulation_thickness": 0.050000000000000003, 
                "turns_number": 13
            }, 
            "layer_10": {
                "conductor_width": 0.40000000000000002, 
                "conductor_height": 2.0, 
                "insulation_thickness": 0.050000000000000003, 
                "turns_number": 13
            }
        }
    }, 
    "setup_definition": {
        "core_material": "4F1", 
        "coil_material": "Copper", 
        "adaptive_frequency": "100.0", 
        "draw_skin_layers": false, 
        "percentage_error": "1.0", 
        "number_passes": 5, 
        "transformer_sides": 2, 
        "side_loads": [
            9.9999999999999995e-07, 
            9.9999999999999995e-07
        ], 
        "excitation_strategy": "Voltage", 
        "voltage": "1.0", 
        "offset": "50.0", 
        "full_model": false, 
        "project_path": "C:/Files/", 
        "frequency_sweep_definition": {
            "frequency_sweep": false
        }, 
        "layer_side_definition": {
            "1": [
                "1", 
                "2", 
                "9", 
                "10"
            ], 
            "2": [
                "3", 
                "4", 
                "5", 
                "6", 
                "7", 
                "8"
            ]
        }, 
        "connections_definition": {
            "1": {
                "P2": {
                    "1": "Layer", 
                    "2": "Layer", 
                    "9": "Layer", 
                    "10": "Layer"
                }
            }, 
            "2": {
                "S3": {
                    "3": "Layer", 
                    "4": "Layer", 
                    "5": "Layer", 
                    "6": "Layer", 
                    "7": "Layer", 
                    "8": "Layer"
                }
            }
        }
    }
}